{"nodes": [{"id": "c_users_george_desktop_truenorth_app_readme_md", "label": "README.md", "file_type": "document", "source_file": "C:\\Users\\George\\Desktop\\truenorth_app\\README.md", "source_location": "L1"}, {"id": "truenorth_app_readme_truenorth_app", "label": "truenorth_app", "file_type": "document", "source_file": "C:\\Users\\George\\Desktop\\truenorth_app\\README.md", "source_location": "L1"}, {"id": "truenorth_app_readme_getting_started", "label": "Getting Started", "file_type": "document", "source_file": "C:\\Users\\George\\Desktop\\truenorth_app\\README.md", "source_location": "L5"}], "edges": [{"source": "c_users_george_desktop_truenorth_app_readme_md", "target": "truenorth_app_readme_truenorth_app", "relation": "contains", "confidence": "EXTRACTED", "source_file": "C:\\Users\\George\\Desktop\\truenorth_app\\README.md", "source_location": "L1", "weight": 1.0}, {"source": "truenorth_app_readme_truenorth_app", "target": "truenorth_app_readme_getting_started", "relation": "contains", "confidence": "EXTRACTED", "source_file": "C:\\Users\\George\\Desktop\\truenorth_app\\README.md", "source_location": "L5", "weight": 1.0}], "input_tokens": 0, "output_tokens": 0}